stellars_jupyterlab_sublime_theme/__init__.py
stellars_jupyterlab_sublime_theme/_version.py
stellars_jupyterlab_sublime_theme-1.0.82.data/data/share/jupyter/labextensions/stellars_jupyterlab_sublime_theme/package.json
stellars_jupyterlab_sublime_theme-1.0.82.data/data/share/jupyter/labextensions/stellars_jupyterlab_sublime_theme/static/509.a853e4859b4bcb78a4a6.js
stellars_jupyterlab_sublime_theme-1.0.82.data/data/share/jupyter/labextensions/stellars_jupyterlab_sublime_theme/static/remoteEntry.7b10a64ce428a06d1607.js
stellars_jupyterlab_sublime_theme-1.0.82.data/data/share/jupyter/labextensions/stellars_jupyterlab_sublime_theme/static/style.js
stellars_jupyterlab_sublime_theme-1.0.82.data/data/share/jupyter/labextensions/stellars_jupyterlab_sublime_theme/static/third-party-licenses.json
stellars_jupyterlab_sublime_theme-1.0.82.data/data/share/jupyter/labextensions/stellars_jupyterlab_sublime_theme/themes/stellars_jupyterlab_sublime_theme/index.css
stellars_jupyterlab_sublime_theme-1.0.82.data/data/share/jupyter/labextensions/stellars_jupyterlab_sublime_theme/themes/stellars_jupyterlab_sublime_theme/index.js
stellars_jupyterlab_sublime_theme-1.0.82.data/data/share/jupyter/labextensions/stellars_jupyterlab_sublime_theme/install.json
stellars_jupyterlab_sublime_theme-1.0.82.dist-info/METADATA
stellars_jupyterlab_sublime_theme-1.0.82.dist-info/WHEEL
stellars_jupyterlab_sublime_theme-1.0.82.dist-info/licenses/LICENSE
stellars_jupyterlab_sublime_theme-1.0.82.dist-info/RECORD
