Metadata-Version: 2.4
Name: stellars_jupyterlab_sublime_theme
Version: 1.0.82
Summary: Dark theme based on Sublime text editor default dark theme, tweaked by Stellars
Project-URL: Homepage, https://github.com/stellarshenson/jupyterlab_stellars_sublime_theme
Project-URL: Bug Tracker, https://github.com/stellarshenson/jupyterlab_stellars_sublime_theme/issues
Project-URL: Repository, https://github.com/stellarshenson/jupyterlab_stellars_sublime_theme.git
Author-email: Konrad Jelen <konrad.jelen@gmail.com>
License: BSD 3-Clause License
License-File: LICENSE
Keywords: jupyter,jupyterlab,jupyterlab-extension
Classifier: Framework :: Jupyter
Classifier: Framework :: Jupyter :: JupyterLab
Classifier: Framework :: Jupyter :: JupyterLab :: 4
Classifier: Framework :: Jupyter :: JupyterLab :: Extensions
Classifier: Framework :: Jupyter :: JupyterLab :: Extensions :: Prebuilt
Classifier: License :: OSI Approved :: BSD License
Classifier: Programming Language :: Python
Classifier: Programming Language :: Python :: 3
Classifier: Programming Language :: Python :: 3.8
Classifier: Programming Language :: Python :: 3.9
Classifier: Programming Language :: Python :: 3.10
Classifier: Programming Language :: Python :: 3.11
Classifier: Programming Language :: Python :: 3.12
Requires-Python: >=3.8
